openseespylinux/LICENSE.md
openseespylinux/__init__.py
openseespylinux/opensees.so
openseespylinux/lib/__init__.py
openseespylinux/lib/libblas.so.3
openseespylinux/lib/libgfortran.so.4
openseespylinux/lib/libgomp.so.1
openseespylinux/lib/liblapack.so.3
openseespylinux/lib/libquadmath.so.0
openseespylinux-3.7.0.6.dist-info/METADATA
openseespylinux-3.7.0.6.dist-info/WHEEL
openseespylinux-3.7.0.6.dist-info/top_level.txt
openseespylinux-3.7.0.6.dist-info/RECORD
