Metadata-Version: 2.1
Name: openseespylinux
Version: 3.7.0.6
Summary: A OpenSeesPy Linux package
Home-page: https://github.com/zhuminjie/openseespy
Author: Minjie Zhu
Author-email: zhum@oregonstate.edu
License: LICENSE.md
Platform: Linux
Classifier: Programming Language :: Python :: 3
Classifier: Operating System :: POSIX :: Linux
Requires-Python: >=3.8
